{
	"class" : {
		"newWith:and:map:" : "DS 7/7/2022 10:04" },
	"instance" : {
		"characterAdministration" : "JA 5/26/2022 12:09",
		"characterAdministration:" : "JA 5/26/2022 12:09",
		"createCharacterSheetButtonSpecWith:" : "RK 5/15/2022 21:05",
		"createDiceToolButtonSpecWith:" : "RK 6/30/2022 01:20",
		"createRulerToolButtonSpecWith:" : "RK 6/30/2022 01:49",
		"createSpecWith:" : "RK 5/15/2022 21:05",
		"darkButtonFocusColor" : "RK 6/30/2022 02:52",
		"diceTool" : "ML 6/26/2022 14:59",
		"diceTool:" : "ML 6/26/2022 14:59",
		"diceToolButtonColor" : "RK 6/30/2022 03:19",
		"initialize" : "RK 6/30/2022 02:14",
		"inputField" : "ML 6/1/2022 18:34",
		"inputField:" : "ML 6/1/2022 18:34",
		"isDiceToolActive" : "DS 7/7/2022 13:41",
		"isDiceToolToBeOpened" : "RK 6/30/2022 03:13",
		"isRulerToolActive" : "RK 6/30/2022 01:51",
		"lightButtonFocusColor" : "RK 6/30/2022 02:51",
		"map" : "OB 6/13/2022 08:41",
		"map:" : "OB 6/13/2022 08:41",
		"notifyDiceToolClosed" : "DS 7/7/2022 10:35",
		"notifyRulerToolClosed" : "DS 7/7/2022 10:34",
		"openCharacterSheetDisplay" : "ML 7/12/2022 18:12",
		"openDiceToolDisplay" : "DS 7/7/2022 16:03",
		"openRulerTool" : "DS 7/7/2022 10:44",
		"rulerToolButtonColor" : "RK 6/30/2022 02:52",
		"subWindowManager" : "DS 7/7/2022 15:13",
		"subWindowManager:" : "DS 7/7/2022 15:13" } }
