{
	"class" : {
		 },
	"instance" : {
		"build" : "MM 5/14/2021 17:09",
		"buildAndOpen" : "joda 5/14/2021 16:40",
		"builder" : "joda 5/14/2021 16:39",
		"builder:" : "joda 5/14/2021 16:41",
		"currentScreen" : "joda 5/14/2021 16:41",
		"currentScreen:" : "joda 5/14/2021 16:41",
		"game" : "joda 5/14/2021 16:42",
		"game:" : "joda 5/14/2021 16:42",
		"initialize" : "piabeeck 5/15/2021 09:09",
		"openGameScreen" : "MM 5/14/2021 17:06",
		"openPlayerCountScreen" : "joda 5/14/2021 16:20",
		"openPlayerNamesScreen" : "piabeeck 5/15/2021 09:14",
		"spec" : "joda 5/14/2021 16:42",
		"spec:" : "MM 5/14/2021 16:56" } }
